{
  "lastUpdated": "2026-05-27 02:34:39",
  "date": "2026-05-27",
  "source": "https://orzice.com/v/index",
  "items": [
    {
      "date": "2026-05-27",
      "mapName": "零号大坝",
      "password": "9329",
      "updatedAt": "2026-05-27 02:34:39",
      "source": "https://orzice.com/v/index",
      "status": "published"
    },
    {
      "date": "2026-05-27",
      "mapName": "长弓溪谷",
      "password": "7271",
      "updatedAt": "2026-05-27 02:34:39",
      "source": "https://orzice.com/v/index",
      "status": "published"
    },
    {
      "date": "2026-05-27",
      "mapName": "巴克什",
      "password": "1741",
      "updatedAt": "2026-05-27 02:34:39",
      "source": "https://orzice.com/v/index",
      "status": "published"
    },
    {
      "date": "2026-05-27",
      "mapName": "航天基地",
      "password": "5559",
      "updatedAt": "2026-05-27 02:34:39",
      "source": "https://orzice.com/v/index",
      "status": "published"
    },
    {
      "date": "2026-05-27",
      "mapName": "潮汐监狱",
      "password": "2863",
      "updatedAt": "2026-05-27 02:34:39",
      "source": "https://orzice.com/v/index",
      "status": "published"
    }
  ]
}
