{
  "lastUpdated": "2026-05-25 04:15:15",
  "date": "2026-05-25",
  "source": "https://orzice.com/v/index",
  "items": [
    {
      "date": "2026-05-25",
      "mapName": "零号大坝",
      "password": "5298",
      "updatedAt": "2026-05-25 04:15:15",
      "source": "https://orzice.com/v/index",
      "status": "published"
    },
    {
      "date": "2026-05-25",
      "mapName": "长弓溪谷",
      "password": "5257",
      "updatedAt": "2026-05-25 04:15:15",
      "source": "https://orzice.com/v/index",
      "status": "published"
    },
    {
      "date": "2026-05-25",
      "mapName": "巴克什",
      "password": "5234",
      "updatedAt": "2026-05-25 04:15:15",
      "source": "https://orzice.com/v/index",
      "status": "published"
    },
    {
      "date": "2026-05-25",
      "mapName": "航天基地",
      "password": "5266",
      "updatedAt": "2026-05-25 04:15:15",
      "source": "https://orzice.com/v/index",
      "status": "published"
    },
    {
      "date": "2026-05-25",
      "mapName": "潮汐监狱",
      "password": "0514",
      "updatedAt": "2026-05-25 04:15:15",
      "source": "https://orzice.com/v/index",
      "status": "published"
    }
  ]
}
