{
  "lastUpdated": "2026-07-22 01:39:53",
  "date": "2026-07-22",
  "source": "https://orzice.com/v/index",
  "items": [
    {
      "date": "2026-07-22",
      "mapName": "零号大坝",
      "password": "6949",
      "updatedAt": "2026-07-22 01:39:53",
      "source": "https://orzice.com/v/index",
      "status": "published"
    },
    {
      "date": "2026-07-22",
      "mapName": "长弓溪谷",
      "password": "0956",
      "updatedAt": "2026-07-22 01:39:53",
      "source": "https://orzice.com/v/index",
      "status": "published"
    },
    {
      "date": "2026-07-22",
      "mapName": "巴克什",
      "password": "8453",
      "updatedAt": "2026-07-22 01:39:53",
      "source": "https://orzice.com/v/index",
      "status": "published"
    },
    {
      "date": "2026-07-22",
      "mapName": "航天基地",
      "password": "2404",
      "updatedAt": "2026-07-22 01:39:53",
      "source": "https://orzice.com/v/index",
      "status": "published"
    },
    {
      "date": "2026-07-22",
      "mapName": "潮汐监狱",
      "password": "2404",
      "updatedAt": "2026-07-22 01:39:53",
      "source": "https://orzice.com/v/index",
      "status": "published"
    }
  ]
}
